bidfx/__init__.py
bidfx/_bidfx_api.py
bidfx/exceptions.py
bidfx/session.py
bidfx/pricing/__init__.py
bidfx/pricing/_service_connector.py
bidfx/pricing/_subject_builder.py
bidfx/pricing/callbacks.py
bidfx/pricing/events.py
bidfx/pricing/field.py
bidfx/pricing/pricing.py
bidfx/pricing/provider.py
bidfx/pricing/subject.py
bidfx/pricing/tenor.py
bidfx/pricing/_pixie/__init__.py
bidfx/pricing/_pixie/control_operations.py
bidfx/pricing/_pixie/pixie_provider.py
bidfx/pricing/_pixie/subscription_register.py
bidfx/pricing/_pixie/message/__init__.py
bidfx/pricing/_pixie/message/ack_message.py
bidfx/pricing/_pixie/message/data_dictionary_message.py
bidfx/pricing/_pixie/message/field_def_message.py
bidfx/pricing/_pixie/message/grant_message.py
bidfx/pricing/_pixie/message/heartbeat_message.py
bidfx/pricing/_pixie/message/login_message.py
bidfx/pricing/_pixie/message/pixie_message_type.py
bidfx/pricing/_pixie/message/price_sync_message.py
bidfx/pricing/_pixie/message/subscription_sync_message.py
bidfx/pricing/_pixie/message/welcome_message.py
bidfx/pricing/_pixie/util/__init__.py
bidfx/pricing/_pixie/util/buffer_reads.py
bidfx/pricing/_pixie/util/compression.py
bidfx/pricing/_pixie/util/varint.py
bidfx/pricing/_puffin/__init__.py
bidfx/pricing/_puffin/element.py
bidfx/pricing/_puffin/message_compressor.py
bidfx/pricing/_puffin/message_decompressor.py
bidfx/pricing/_puffin/puffin_provider.py
bidfx/pricing/_puffin/token_dictionary.py
tests/__init__.py
tests/test_session.py
tests/pixie/__init__.py
tests/pixie/test_subscription_register.py
tests/pixie/field_def_tests/__init__.py
tests/pixie/field_def_tests/test_field_def_encoding.py
tests/pixie/field_def_tests/test_field_def_types.py
tests/pixie/messages_tests/__init__.py
tests/pixie/messages_tests/test_ack_message.py
tests/pixie/messages_tests/test_data_dictionary_message.py
tests/pixie/messages_tests/test_grant_message.py
tests/pixie/messages_tests/test_heartbeat_message.py
tests/pixie/messages_tests/test_login_message.py
bidfx_api-1.1.4.dist-info/LICENSE-2.0.txt
bidfx_api-1.1.4.dist-info/METADATA
bidfx_api-1.1.4.dist-info/WHEEL
bidfx_api-1.1.4.dist-info/top_level.txt
bidfx_api-1.1.4.dist-info/RECORD
