Metadata-Version: 2.1
Name: bidfx-api
Version: 1.1.4
Summary: Public API for accessing the BidFX platform for pricing
Home-page: https://github.com/bidfx/bidfx-api-py
Author: Paul Sweeny
Author-email: paul.sweeny@bidfx.com
License: Apache License 2.0
Download-URL: https://github.com/bidfx/bidfx-api-py/tarball/v1.1.4
Platform: UNKNOWN
Classifier: Programming Language :: Python :: 3.6
Classifier: Programming Language :: Python :: 3.7
Classifier: License :: OSI Approved :: Apache Software License
Classifier: Operating System :: OS Independent
Classifier: Intended Audience :: Financial and Insurance Industry
Classifier: Topic :: Office/Business :: Financial :: Investment
Classifier: Natural Language :: English
Classifier: Development Status :: 5 - Production/Stable
Requires-Python: >=3.6
License-File: LICENSE-2.0.txt
Requires-Dist: pycryptodomex (==3.9.4)
